{"license":"Apache 2.0","tarball_file_size":24608,"version":"1.2.0","published_at":"2017-04-11T06:49:11Z","average_rating":null,"cookbook":"https://supermarket.chef.io/api/v1/cookbooks/ruby_rbenv","file":"https://supermarket.chef.io/api/v1/cookbooks/ruby_rbenv/versions/1.2.0/download","quality_metrics":[{"name":"Supported Platforms","failed":false,"feedback":"ruby_rbenv supports at least one platform."},{"name":"Contributing File","failed":false,"feedback":"passed the CONTRIBUTING.md file metric."},{"name":"Collaborator Number","failed":false,"feedback":"passed the Collaborators Metric with 3 collaborators."},{"name":"No Binaries","failed":false,"feedback":"passed the No Binaries metric. Contains no obvious binaries."},{"name":"Version Tag","failed":false,"feedback":"passed the version tag metric."},{"name":"Publish","failed":false,"feedback":"ruby_rbenv passed the publish metric"},{"name":"Foodcritic","failed":false,"feedback":"\nRun with Foodcritic Version 10.3.1 with tags metadata,correctness ~FC031 ~FC045 and failure tags any"},{"name":"License","failed":false,"feedback":"ruby_rbenv has a recognized open source license."},{"name":"Testing File","failed":true,"feedback":"Failure: To pass this metric, your cookbook metadata must include a source url, the source url must be in the form of http://github.com/user/repo, and your repo must contain a TESTING.md file"}],"supports":{"centos":">= 0.0.0","fedora":">= 0.0.0","freebsd":">= 0.0.0","debian":">= 0.0.0","ubuntu":">= 0.0.0","redhat":">= 0.0.0","suse":">= 0.0.0","gentoo":">= 0.0.0","arch":">= 0.0.0","mac_os_x":">= 0.0.0","scientific":">= 0.0.0","amazon":">= 0.0.0","linuxmint":">= 0.0.0"},"dependencies":{"ruby_build":">= 1.1.0"}}